frostbound/__init__.py
frostbound/py.typed
frostbound/experiments/__init__.py
frostbound/experiments/builder.py
frostbound/experiments/constants.py
frostbound/experiments/experiment.py
frostbound/experiments/models.py
frostbound/experiments/protocols.py
frostbound/experiments/storage.py
frostbound/experiments/types.py
frostbound/instrumentation/__init__.py
frostbound/instrumentation/timer.py
frostbound/monads/__init__.py
frostbound/monads/either.py
frostbound/monads/maybe.py
frostbound/proxy/__init__.py
frostbound/proxy/immutable.py
frostbound/pydanticonf/__init__.py
frostbound/pydanticonf/_instantiate.py
frostbound/pydanticonf/base.py
frostbound/pydanticonf/factory.py
frostbound/pydanticonf/settings.py
frostbound/pydanticonf/types.py
frostbound/pydanticonf/utils.py
frostbound/resilience/__init__.py
frostbound/resilience/circuit_breaker.py
frostbound/resilience/retry.py
frostbound/structured/__init__.py
frostbound/structured/config.py
frostbound/structured/factory.py
frostbound/structured/hooks.py
frostbound/structured/types.py
frostbound/structured/adapters/__init__.py
frostbound/structured/adapters/anthropic.py
frostbound/structured/adapters/base.py
frostbound/structured/adapters/gemini.py
frostbound/structured/adapters/openai.py
frostbound/structured/adapters/py.typed
frostbound/versioning/__init__.py
frostbound/versioning/git_info.py
frostbound/wrappers/__init__.py
frostbound/wrappers/instructor.py
frostbound-0.8.0.dist-info/METADATA
frostbound-0.8.0.dist-info/WHEEL
frostbound-0.8.0.dist-info/licenses/LICENSE
frostbound-0.8.0.dist-info/RECORD
