Metadata-Version: 2.4
Name: frostbound
Version: 0.8.0
Summary: Enterprise-grade Python utilities.
Author-email: GAO Hongnan <hongnangao@gmail.com>
License: MIT
License-File: LICENSE
Classifier: Development Status :: 4 - Beta
Classifier: Intended Audience :: Developers
Classifier: License :: OSI Approved :: MIT License
Classifier: Programming Language :: Python :: 3.12
Classifier: Typing :: Typed
Requires-Python: >=3.12
Requires-Dist: anthropic>=0.55.0
Requires-Dist: google-genai>=1.27.0
Requires-Dist: google-generativeai>=0.8.5
Requires-Dist: instructor>=1.9.0
Requires-Dist: omegaconf>=2.3.0
Requires-Dist: pydantic-settings>=2.9.1
Requires-Dist: pydantic>=2.0.0
Requires-Dist: pyyaml>=6.0.2
Requires-Dist: rich
Provides-Extra: dev
Requires-Dist: black>=25.1.0; extra == 'dev'
Requires-Dist: isort>=6.0.1; extra == 'dev'
Requires-Dist: mypy>=1.16.0; extra == 'dev'
Requires-Dist: pyright>=1.1.402; extra == 'dev'
Requires-Dist: pytest-asyncio>=0.21.0; extra == 'dev'
Requires-Dist: pytest-cov>=4.1.0; extra == 'dev'
Requires-Dist: pytest-mock>=3.14.1; extra == 'dev'
Requires-Dist: pytest>=8.4.0; extra == 'dev'
Requires-Dist: ruff>=0.11.13; extra == 'dev'
Requires-Dist: ty>=0.0.1a10; extra == 'dev'
Requires-Dist: types-pyyaml>=6.0.12.20250516; extra == 'dev'
